odoo8_addon_product_serial-8.0.1.0.0.99.dev8-nspkg.pth
odoo_addons/product_serial/README.rst
odoo_addons/product_serial/__init__.py
odoo_addons/product_serial/__openerp__.py
odoo_addons/product_serial/product.py
odoo_addons/product_serial/product_demo.xml
odoo_addons/product_serial/product_view.xml
odoo_addons/product_serial/i18n/de.po
odoo_addons/product_serial/i18n/es.po
odoo_addons/product_serial/i18n/fr.po
odoo_addons/product_serial/i18n/fr.po.moved
odoo_addons/product_serial/i18n/fr_BE.po
odoo_addons/product_serial/i18n/product_serial.pot
odoo_addons/product_serial/i18n/sv.po
odoo_addons/product_serial/migrations/8.0.1.0.0/post-migration.py
odoo_addons/product_serial/static/description/icon.png
odoo_addons/product_serial/wizard/__init__.py
odoo_addons/product_serial/wizard/prodlot_wizard.py
odoo_addons/product_serial/wizard/prodlot_wizard_view.xml
odoo_addons/product_serial/wizard/stock_transfer_details.py
odoo8_addon_product_serial-8.0.1.0.0.99.dev8.dist-info/METADATA
odoo8_addon_product_serial-8.0.1.0.0.99.dev8.dist-info/WHEEL
odoo8_addon_product_serial-8.0.1.0.0.99.dev8.dist-info/namespace_packages.txt
odoo8_addon_product_serial-8.0.1.0.0.99.dev8.dist-info/top_level.txt
odoo8_addon_product_serial-8.0.1.0.0.99.dev8.dist-info/RECORD
